[
  { "id": 1, "text": "Je pense, donc je suis.", "author": "René Descartes", "isFavorite": false },
  { "id": 2, "text": "Le cœur a ses raisons que la raison ne connaît point.", "author": "Blaise Pascal", "isFavorite": false },
  { "id": 3, "text": "On ne voit bien qu’avec le cœur. L’essentiel est invisible pour les yeux.", "author": "Antoine de Saint-Exupéry", "isFavorite": false },
  { "id": 4, "text": "Rien ne sert de courir ; il faut partir à point.", "author": "Jean de La Fontaine", "isFavorite": false },
  { "id": 5, "text": "À vaincre sans péril, on triomphe sans gloire.", "author": "Pierre Corneille", "isFavorite": false },
  { "id": 6, "text": "Le mieux est l’ennemi du bien.", "author": "Voltaire", "isFavorite": false },
  { "id": 7, "text": "Il faut cultiver notre jardin.", "author": "Voltaire", "isFavorite": false },
  { "id": 8, "text": "L’homme est né libre, et partout il est dans les fers.", "author": "Jean-Jacques Rousseau", "isFavorite": false },
  { "id": 9, "text": "Sans la liberté de blâmer, il n’est point d’éloge flatteur.", "author": "Beaumarchais", "isFavorite": false },
  { "id": 10, "text": "La liberté est le droit de faire tout ce que les lois permettent.", "author": "Montesquieu", "isFavorite": false },
  { "id": 11, "text": "La vérité est en marche et rien ne l’arrêtera.", "author": "Émile Zola", "isFavorite": false },
  { "id": 12, "text": "Il faut imaginer Sisyphe heureux.", "author": "Albert Camus", "isFavorite": true },
  { "id": 13, "text": "L’enfer, c’est les autres.", "author": "Jean-Paul Sartre", "isFavorite": false },
  { "id": 14, "text": "Homme libre, toujours tu chériras la mer !", "author": "Charles Baudelaire", "isFavorite": false },
  { "id": 15, "text": "Qu’importe le flacon, pourvu qu’on ait l’ivresse.", "author": "Alfred de Musset", "isFavorite": true },
  { "id": 16, "text": "On n’est jamais si heureux ni si malheureux qu’on se l’imagine.", "author": "François de La Rochefoucauld", "isFavorite": false },
  { "id": 17, "text": "La plus perdue de toutes les journées est celle où l’on n’a pas ri.", "author": "Chamfort", "isFavorite": false },
  { "id": 18, "text": "Ce que l’on conçoit bien s’énonce clairement, et les mots pour le dire arrivent aisément.", "author": "Nicolas Boileau", "isFavorite": false },
  { "id": 19, "text": "Science sans conscience n’est que ruine de l’âme.", "author": "François Rabelais", "isFavorite": false },
  { "id": 20, "text": "Cueillez dès aujourd’hui les roses de la vie.", "author": "Pierre de Ronsard", "isFavorite": false },
  { "id": 21, "text": "Le vent se lève !… il faut tenter de vivre !", "author": "Paul Valéry", "isFavorite": false },
  { "id": 22, "text": "Il n’y a pas d’amour heureux.", "author": "Louis Aragon", "isFavorite": false },
  { "id": 23, "text": "Je est un autre.", "author": "Arthur Rimbaud", "isFavorite": false },
  { "id": 24, "text": "De la musique avant toute chose.", "author": "Paul Verlaine", "isFavorite": false },
  { "id": 25, "text": "Il est grand temps de rallumer les étoiles.", "author": "Guillaume Apollinaire", "isFavorite": false },
  { "id": 26, "text": "Ce que l’on te reproche, cultive-le : c’est toi.", "author": "Jean Cocteau", "isFavorite": false },
  { "id": 27, "text": "Les grandes pensées viennent du cœur.", "author": "Vauvenargues", "isFavorite": false },
  { "id": 28, "text": "Tout est dit, et l’on vient trop tard.", "author": "Jean de La Bruyère", "isFavorite": false },
  { "id": 29, "text": "La mélancolie, c’est le bonheur d’être triste.", "author": "Victor Hugo", "isFavorite": false },
  { "id": 30, "text": "La raison du plus fort est toujours la meilleure.", "author": "Jean de La Fontaine", "isFavorite": false },
  { "id": 31, "text": "Aide-toi, le ciel t’aidera.", "author": "Jean de La Fontaine", "isFavorite": false },
  { "id": 32, "text": "Tel est pris qui croyait prendre.", "author": "Jean de La Fontaine", "isFavorite": false },
  { "id": 33, "text": "Que sais-je ?", "author": "Michel de Montaigne", "isFavorite": false },
  { "id": 34, "text": "Parce que c’était lui, parce que c’était moi.", "author": "Michel de Montaigne", "isFavorite": false },
  { "id": 35, "text": "Ce qui ne me tue pas me rend plus fort.", "author": "Friedrich Nietzsche", "isFavorite": false },
  { "id": 36, "text": "Le suprême art de la guerre, c’est de soumettre l’ennemi sans combat.", "author": "Sun Tzu", "isFavorite": false },
  { "id": 37, "text": "Un voyage de mille lieues commence toujours par un premier pas.", "author": "Lao Tseu", "isFavorite": false },
  { "id": 38, "text": "Aie le courage de te servir de ton propre entendement !", "author": "Immanuel Kant", "isFavorite": false },
  { "id": 39, "text": "Ne pas rire, ne pas déplorer, ne pas détester, mais comprendre.", "author": "Baruch Spinoza", "isFavorite": false },
  { "id": 40, "text": "Rien de grand ne s’est accompli sans passion.", "author": "G. W. F. Hegel", "isFavorite": false },
  { "id": 41, "text": "La vie d’un homme est ce que ses pensées en font.", "author": "Marc Aurèle", "isFavorite": false },
  { "id": 42, "text": "Ce qui trouble les hommes, ce ne sont pas les choses, mais les jugements qu’ils portent sur les choses.", "author": "Épictète", "isFavorite": false },
  { "id": 43, "text": "On ne se baigne jamais deux fois dans le même fleuve.", "author": "Héraclite", "isFavorite": false },
  { "id": 44, "text": "L’ami est un autre soi-même.", "author": "Aristote", "isFavorite": false },
  { "id": 45, "text": "O tempora ! O mores !", "author": "Cicéron", "isFavorite": false },
  { "id": 46, "text": "Être ou ne pas être, telle est la question.", "author": "William Shakespeare", "isFavorite": false },
  { "id": 47, "text": "La beauté sauvera le monde.", "author": "Fiodor Dostoïevski", "isFavorite": false },
  { "id": 48, "text": "La brièveté est sœur du talent.", "author": "Anton Tchekhov", "isFavorite": false },
  { "id": 49, "text": "Un livre doit être la hache qui brise la mer gelée en nous.", "author": "Franz Kafka", "isFavorite": false },
  { "id": 50, "text": "Le meilleur moyen de prédire l’avenir est de l’inventer.", "author": "Alan Kay", "isFavorite": false },
  { "id": 51, "text": "Le pouvoir tend à corrompre, le pouvoir absolu corrompt absolument.", "author": "Lord Acton", "isFavorite": false },
  { "id": 52, "text": "La vérité vous rendra libres.", "author": "Évangile selon Jean", "isFavorite": false },
  { "id": 53, "text": "Il y a un temps pour tout.", "author": "Livre de l’Ecclésiaste", "isFavorite": false },
  { "id": 54, "text": "Demandez, et l’on vous donnera ; cherchez, et vous trouverez.", "author": "Évangile selon Matthieu", "isFavorite": false },
  { "id": 55, "text": "Aime ton prochain comme toi-même.", "author": "Évangile selon Matthieu", "isFavorite": false },
  { "id": 56, "text": "L’amour est patient, il est plein de bonté.", "author": "Première épître aux Corinthiens", "isFavorite": false },
  { "id": 57, "text": "Ne jugez point, afin de n’être point jugés.", "author": "Évangile selon Matthieu", "isFavorite": false },
  { "id": 58, "text": "Qui sème le vent récolte la tempête.", "author": "Livre d’Osée", "isFavorite": false },
  { "id": 59, "text": "Heureux les artisans de paix, car ils seront appelés fils de Dieu.", "author": "Évangile selon Matthieu", "isFavorite": false },
  { "id": 60, "text": "Là où est ton trésor, là aussi sera ton cœur.", "author": "Évangile selon Matthieu", "isFavorite": false },
  { "id": 61, "text": "Carpe diem.", "author": "Horace", "isFavorite": false },
  { "id": 62, "text": "Veni, vidi, vici.", "author": "Jules César", "isFavorite": false },
  { "id": 63, "text": "Alea jacta est.", "author": "Jules César", "isFavorite": false },
  { "id": 64, "text": "Mens sana in corpore sano.", "author": "Juvénal", "isFavorite": false },
  { "id": 65, "text": "Amor vincit omnia.", "author": "Virgile", "isFavorite": false },
  { "id": 66, "text": "Audentes fortuna iuvat.", "author": "Virgile", "isFavorite": false },
  { "id": 67, "text": "Festina lente.", "author": "Proverbe latin", "isFavorite": false },
  { "id": 68, "text": "Memento mori.", "author": "Proverbe latin", "isFavorite": false },
  { "id": 69, "text": "Per aspera ad astra.", "author": "Proverbe latin", "isFavorite": false },
  { "id": 70, "text": "In vino veritas.", "author": "Proverbe latin", "isFavorite": false },
  { "id": 71, "text": "Tempus fugit.", "author": "Proverbe latin", "isFavorite": false },
  { "id": 72, "text": "Verba volant, scripta manent.", "author": "Proverbe latin", "isFavorite": false },
  { "id": 73, "text": "Repetita iuvant.", "author": "Proverbe latin", "isFavorite": false },
  { "id": 74, "text": "Nulla dies sine linea.", "author": "Proverbe latin", "isFavorite": false },
  { "id": 75, "text": "Divide et impera.", "author": "Proverbe latin", "isFavorite": false },
  { "id": 76, "text": "Pierre qui roule n’amasse pas mousse.", "author": "Proverbe français", "isFavorite": false },
  { "id": 77, "text": "Après la pluie, le beau temps.", "author": "Proverbe français", "isFavorite": false },
  { "id": 78, "text": "Qui vivra verra.", "author": "Proverbe français", "isFavorite": false },
  { "id": 79, "text": "Mieux vaut tard que jamais.", "author": "Proverbe français", "isFavorite": false },
  { "id": 80, "text": "L’union fait la force.", "author": "Proverbe français", "isFavorite": false },
  { "id": 81, "text": "L’occasion fait le larron.", "author": "Proverbe français", "isFavorite": false },
  { "id": 82, "text": "Petit à petit, l’oiseau fait son nid.", "author": "Proverbe français", "isFavorite": false },
  { "id": 83, "text": "Chacun voit midi à sa porte.", "author": "Proverbe français", "isFavorite": false },
  { "id": 84, "text": "Qui se ressemble s’assemble.", "author": "Proverbe français", "isFavorite": false },
  { "id": 85, "text": "Quand on veut, on peut.", "author": "Proverbe français", "isFavorite": false },
  { "id": 86, "text": "À quelque chose malheur est bon.", "author": "Proverbe français", "isFavorite": false },
  { "id": 87, "text": "On n’est jamais mieux servi que par soi-même.", "author": "Proverbe français", "isFavorite": false },
  { "id": 88, "text": "Aux grands maux les grands remèdes.", "author": "Proverbe français", "isFavorite": false },
  { "id": 89, "text": "Les bons comptes font les bons amis.", "author": "Proverbe français", "isFavorite": false },
  { "id": 90, "text": "Nul n’est prophète en son pays.", "author": "Proverbe français", "isFavorite": false },
  { "id": 91, "text": "À l’impossible nul n’est tenu.", "author": "Proverbe français", "isFavorite": false },
  { "id": 92, "text": "L’habit ne fait pas le moine.", "author": "Proverbe français", "isFavorite": false },
  { "id": 93, "text": "Il n’y a pas de fumée sans feu.", "author": "Proverbe français", "isFavorite": false },
  { "id": 94, "text": "Tant va la cruche à l’eau qu’à la fin elle se casse.", "author": "Proverbe français", "isFavorite": false },
  { "id": 95, "text": "Qui aime bien châtie bien.", "author": "Proverbe français", "isFavorite": false },
  { "id": 96, "text": "Faute de grives, on mange des merles.", "author": "Proverbe français", "isFavorite": false },
  { "id": 97, "text": "Loin des yeux, loin du cœur.", "author": "Proverbe français", "isFavorite": false },
  { "id": 98, "text": "Qui dort dîne.", "author": "Proverbe français", "isFavorite": false },
  { "id": 99, "text": "Un tiens vaut mieux que deux tu l’auras.", "author": "Proverbe français", "isFavorite": false },
  { "id": 100, "text": "On ne fait pas d’omelette sans casser des œufs.", "author": "Proverbe français", "isFavorite": false },
  {"id":101,"text":"La vie est un mystère qu’il faut vivre, et non un problème à résoudre.","author":"Gandhi","isFavorite":false,"theme":"philosophy"},
     {"id":102,"text":"Le succès n’est pas la clé du bonheur. Le bonheur est la clé du succès.","author":"Albert Schweitzer","isFavorite":false,"theme":"motivation"},
     {"id":103,"text":"On ne voit bien qu’avec le cœur. L’essentiel est invisible pour les yeux.","author":"Antoine de Saint-Exupéry","isFavorite":false,"theme":"wisdom"},
     {"id":104,"text":"Fais de ta vie un rêve, et d’un rêve, une réalité.","author":"Antoine de Saint-Exupéry","isFavorite":false,"theme":"motivation"},
     {"id":105,"text":"Celui qui déplace une montagne commence par déplacer de petites pierres.","author":"Confucius","isFavorite":false,"theme":"philosophy"},
     {"id":106,"text":"Rien ne se perd, rien ne se crée, tout se transforme.","author":"Antoine Lavoisier","isFavorite":false,"theme":"science"},
     {"id":107,"text":"L’imagination est plus importante que le savoir.","author":"Albert Einstein","isFavorite":false,"theme":"science"},
     {"id":108,"text":"La simplicité est la sophistication suprême.","author":"Leonard de Vinci","isFavorite":false,"theme":"art"},
     {"id":109,"text":"Le courage n’est pas l’absence de peur, mais la capacité de la vaincre.","author":"Nelson Mandela","isFavorite":false,"theme":"wisdom"},
     {"id":110,"text":"Il n’y a qu’une façon d’échouer, c’est d’abandonner avant d’avoir réussi.","author":"Georges Clemenceau","isFavorite":false,"theme":"motivation"},
     {"id":111,"text":"Vis comme si tu devais mourir demain. Apprends comme si tu devais vivre toujours.","author":"Gandhi","isFavorite":false,"theme":"philosophy"},
     {"id":112,"text":"Les enfants seuls savent ce qu'ils cherchent.","author":"Antoine de Saint-Exupéry","isFavorite":false,"theme":"wisdom"},
     {"id":113,"text":"La beauté de l'instant présent n'a pas de prix. Elle se ressent et se vit.","author":"Joëlle Laurencin","isFavorite":false,"theme":"literature"},
     {"id":114,"text":"Vis le présent, et les souvenirs t'accompagneront.","author":"Nabil Alami","isFavorite":false,"theme":"wisdom"},
     {"id":115,"text":"Une photographie est un souvenir en hibernation qui nie l'écoulement du temps.","author":"André Hardellet","isFavorite":false,"theme":"art"},
     {"id":116,"text":"Il faut toujours viser la lune, car même en cas d'échec, on atterrit dans les étoiles.","author":"Oscar Wilde","isFavorite":false,"theme":"motivation"},
     {"id":117,"text":"Le bonheur n’est pas quelque chose de prêt à l’emploi. Il vient de vos propres actions.","author":"Dalaï Lama","isFavorite":false,"theme":"wisdom"},
     {"id":118,"text":"Si vous voulez vivre une vie heureuse, attachez-la à un but, non pas à des personnes ou des choses.","author":"Albert Einstein","isFavorite":false,"theme":"philosophy"},
     {"id":119,"text":"Ne juge pas chaque jour à la récolte que tu fais mais aux graines que tu sèmes.","author":"Robert Louis Stevenson","isFavorite":false,"theme":"motivation"},
     {"id":120,"text":"L’échec est simplement l’opportunité de recommencer, cette fois plus intelligemment.","author":"Henry Ford","isFavorite":false,"theme":"motivation"},
     {"id":121,"text":"La seule limite à notre épanouissement de demain sera nos doutes d’aujourd’hui.","author":"Franklin D. Roosevelt","isFavorite":false,"theme":"wisdom"},
     {"id":122,"text":"Tout ce qui ne te tue pas te rend plus fort.","author":"Friedrich Nietzsche","isFavorite":false,"theme":"wisdom"},
     {"id":123,"text":"Ce n’est pas la force, mais la persévérance qui fait les grandes œuvres.","author":"Samuel Johnson","isFavorite":false,"theme":"wisdom"},
     {"id":124,"text":"Agis comme s’il était impossible d’échouer.","author":"Winston Churchill","isFavorite":false,"theme":"motivation"},
     {"id":125,"text":"Le succès est la somme de petits efforts répétés jour après jour.","author":"Robert Collier","isFavorite":false,"theme":"motivation"},
     {"id":126,"text":"Fais ce que tu peux, avec ce que tu as, là où tu es.","author":"Theodore Roosevelt","isFavorite":false,"theme":"motivation"},
     {"id":127,"text":"Ne crains pas d’avancer lentement, crains seulement de t’arrêter.","author":"Proverbe chinois","isFavorite":false,"theme":"philosophy"},
     {"id":128,"text":"On ne voit bien qu’avec le cœur.","author":"Antoine de Saint-Exupéry","isFavorite":false,"theme":"wisdom"},
     {"id":129,"text":"La connaissance s’acquiert par l’expérience, tout le reste n’est que de l’information.","author":"Albert Einstein","isFavorite":false,"theme":"science"},
     {"id":130,"text":"Rêve grand, commence petit, mais commence.","author":"Simon Sinek","isFavorite":false,"theme":"motivation"},
     {"id":131,"text":"L’éducation est l’arme la plus puissante pour changer le monde.","author":"Nelson Mandela","isFavorite":false,"theme":"wisdom"},
     {"id":132,"text":"Le véritable signe de l’intelligence n’est pas la connaissance mais l’imagination.","author":"Albert Einstein","isFavorite":false,"theme":"science"},
     {"id":133,"text":"Il n’y a pas de chemin vers le bonheur, le bonheur c’est le chemin.","author":"Bouddha","isFavorite":false,"theme":"philosophy"},
     {"id":134,"text":"Agis sans attendre le résultat.","author":"Confucius","isFavorite":false,"theme":"motivation"},
     {"id":135,"text":"La patience est amère, mais son fruit est doux.","author":"Jean-Jacques Rousseau","isFavorite":false,"theme":"wisdom"},
     {"id":136,"text":"Le savoir parler s’apprend en parlant.","author":"François de La Rochefoucauld","isFavorite":false,"theme":"literature"},
     {"id":137,"text":"Qui ne tente rien n’a rien.","author":"Proverbe français","isFavorite":false,"theme":"motivation"},
     {"id":138,"text":"La vie, c’est comme une bicyclette, il faut avancer pour ne pas perdre l’équilibre.","author":"Albert Einstein","isFavorite":false,"theme":"philosophy"},
     {"id":139,"text":"Le courage consiste à dominer la peur, non pas à l’abolir.","author":"Mark Twain","isFavorite":false,"theme":"wisdom"},
     {"id":140,"text":"Le plus grand risque est de ne prendre aucun risque.","author":"Mark Zuckerberg","isFavorite":false,"theme":"motivation"},
     {"id":141,"text":"Celui qui ouvre une porte d’école, ferme une prison.","author":"Victor Hugo","isFavorite":false,"theme":"literature"},
     {"id":142,"text":"Ne doutez jamais qu’un petit groupe de personnes réfléchies et engagées puisse changer le monde.","author":"Margaret Mead","isFavorite":false,"theme":"motivation"},
     {"id":143,"text":"Chaque homme doit inventer son chemin.","author":"Jean-Paul Sartre","isFavorite":false,"theme":"philosophy"},
     {"id":144,"text":"Il n’est jamais trop tard pour devenir ce que l’on aurait pu être.","author":"George Eliot","isFavorite":false,"theme":"motivation"},
     {"id":145,"text":"Celui qui sait se contenter de peu ne sera jamais pauvre.","author":"Socrate","isFavorite":false,"theme":"wisdom"},
     {"id":146,"text":"On ne naît pas femme : on le devient.","author":"Simone de Beauvoir","isFavorite":false,"theme":"literature"},
     {"id":147,"text":"La liberté consiste à pouvoir faire tout ce qui ne nuit pas à autrui.","author":"Déclaration des droits de l’homme","isFavorite":false,"theme":"politics"},
     {"id":148,"text":"Le plus grand plaisir dans la vie est de réaliser ce que les autres vous pensent incapable de réaliser.","author":"Walter Bagehot","isFavorite":false,"theme":"motivation"},
     {"id":149,"text":"Ne vis pas pour que ta présence se remarque, mais pour que ton absence se sente.","author":"Bob Marley","isFavorite":false,"theme":"wisdom"},
     {"id":150,"text":"Tout ce que l’esprit peut concevoir et croire, il peut l’accomplir.","author":"Napoleon Hill","isFavorite":false,"theme":"motivation"},
     {"id":151,"text":"L’expérience est le nom que chacun donne à ses erreurs.","author":"Oscar Wilde","isFavorite":false,"theme":"wisdom"},
     {"id":152,"text":"Le monde est un livre et ceux qui ne voyagent pas n’en lisent qu’une page.","author":"Saint Augustin","isFavorite":false,"theme":"literature"},
     {"id":153,"text":"Le savoir est le pouvoir.","author":"Francis Bacon","isFavorite":false,"theme":"science"},
     {"id":154,"text":"Tout est difficile avant d’être facile.","author":"Thomas Fuller","isFavorite":false,"theme":"motivation"},
     {"id":155,"text":"Rien n’est permanent, sauf le changement.","author":"Bouddha","isFavorite":false,"theme":"philosophy"},
     {"id":156,"text":"La connaissance parle, mais la sagesse écoute.","author":"Jimi Hendrix","isFavorite":false,"theme":"wisdom"},
     {"id":157,"text":"Il n’y a pas de vent favorable pour celui qui ne sait où il va.","author":"Sénèque","isFavorite":false,"theme":"philosophy"},
     {"id":158,"text":"Le plus grand obstacle à la vie est l’attente, qui espère demain et néglige aujourd’hui.","author":"Sénèque","isFavorite":false,"theme":"wisdom"},
     {"id":159,"text":"Rien ne sert de courir ; il faut partir à point.","author":"Jean de La Fontaine","isFavorite":false,"theme":"literature"},
     {"id":160,"text":"Le meilleur moyen de prédire l’avenir est de le créer.","author":"Peter Drucker","isFavorite":false,"theme":"motivation"},
     {"id":161,"text":"Le succès consiste à aller d’échec en échec sans perdre son enthousiasme.","author":"Winston Churchill","isFavorite":false,"theme":"motivation"},
     {"id":162,"text":"La patience est amère, mais son fruit est doux.","author":"Jean-Jacques Rousseau","isFavorite":false,"theme":"wisdom"},
     {"id":163,"text":"L’art de la réussite consiste à savoir s’entourer des meilleurs.","author":"John Fitzgerald Kennedy","isFavorite":false,"theme":"motivation"},
     {"id":164,"text":"Ce n’est pas parce que les choses sont difficiles que nous n’osons pas, c’est parce que nous n’osons pas qu’elles sont difficiles.","author":"Sénèque","isFavorite":false,"theme":"philosophy"},
     {"id":165,"text":"L’homme est la mesure de toutes choses.","author":"Protagoras","isFavorite":false,"theme":"philosophy"},
     {"id":166,"text":"La lecture est une amitié.","author":"Marcel Proust","isFavorite":false,"theme":"literature"},
     {"id":167,"text":"Ne jugez pas chaque jour à la récolte que vous faites mais aux graines que vous semez.","author":"Robert Louis Stevenson","isFavorite":false,"theme":"motivation"},
     {"id":168,"text":"L’éducation est l’arme la plus puissante pour changer le monde.","author":"Nelson Mandela","isFavorite":false,"theme":"wisdom"},
     {"id":169,"text":"Celui qui veut réussir trouve un moyen, celui qui ne veut rien faire trouve une excuse.","author":"Proverbe chinois","isFavorite":false,"theme":"motivation"},
     {"id":170,"text":"Il n’y a rien de constant si ce n’est le changement.","author":"Bouddha","isFavorite":false,"theme":"philosophy"},
     {"id":171,"text":"Le temps est un grand maître, dit-on, le malheur est qu’il tue ses élèves.","author":"Hector Berlioz","isFavorite":false,"theme":"wisdom"},
     {"id":172,"text":"Il vaut mieux allumer une bougie que maudire l’obscurité.","author":"Confucius","isFavorite":false,"theme":"wisdom"},
     {"id":173,"text":"Ne pas préparer, c’est préparer l’échec.","author":"Benjamin Franklin","isFavorite":false,"theme":"motivation"},
     {"id":174,"text":"Le bonheur est parfois caché dans l’inconnu.","author":"Victor Hugo","isFavorite":false,"theme":"philosophy"},
     {"id":175,"text":"Le vrai bonheur ne dépend d’aucun être, d’aucun objet extérieur.","author":"Dalaï Lama","isFavorite":false,"theme":"wisdom"},
     {"id":176,"text":"L’expérience est le nom que chacun donne à ses erreurs.","author":"Oscar Wilde","isFavorite":false,"theme":"wisdom"},
     {"id":177,"text":"La culture, c’est ce qui reste quand on a tout oublié.","author":"Édouard Herriot","isFavorite":false,"theme":"literature"},
     {"id":178,"text":"Il n’y a pas de hasard, il n’y a que des rendez-vous.","author":"Paul Éluard","isFavorite":false,"theme":"philosophy"},
     {"id":179,"text":"Le monde est un livre, et ceux qui ne voyagent pas n’en lisent qu’une page.","author":"Saint Augustin","isFavorite":false,"theme":"literature"},
     {"id":180,"text":"La vie, ce n’est pas d’attendre que les orages passent, c’est d’apprendre à danser sous la pluie.","author":"Sénèque","isFavorite":false,"theme":"motivation"},
     {"id":181,"text":"Ce que l’on conçoit bien s’énonce clairement.","author":"Boileau","isFavorite":false,"theme":"literature"},
     {"id":182,"text":"La vie est courte, l’art est long, l’occasion fugitive, l’expérience trompeuse, le jugement difficile.","author":"Hippocrate","isFavorite":false,"theme":"wisdom"},
     {"id":183,"text":"La patience et le temps font plus que la force ou la rage.","author":"Jean de La Fontaine","isFavorite":false,"theme":"wisdom"},
     {"id":184,"text":"L’éducation est l’âme d’un peuple qui se transmet de génération en génération.","author":"Gandhi","isFavorite":false,"theme":"wisdom"},
     {"id":185,"text":"La vie est faite de petits bonheurs.","author":"Jacques Brel","isFavorite":false,"theme":"philosophy"},
     {"id":186,"text":"Le travail éloigne de nous trois grands maux : l’ennui, le vice et le besoin.","author":"Voltaire","isFavorite":false,"theme":"philosophy"},
     {"id":187,"text":"Il n’y a pas de génie sans un grain de folie.","author":"Aristote","isFavorite":false,"theme":"wisdom"},
     {"id":188,"text":"La liberté commence où l’ignorance finit.","author":"Victor Hugo","isFavorite":false,"theme":"wisdom"},
     {"id":189,"text":"Rien ne sert de courir, il faut partir à point.","author":"Jean de La Fontaine","isFavorite":false,"theme":"literature"},
     {"id":190,"text":"Tout ce que l’esprit peut concevoir et croire, il peut l’accomplir.","author":"Napoleon Hill","isFavorite":false,"theme":"motivation"},
     {"id":191,"text":"Chaque homme doit inventer son chemin.","author":"Jean-Paul Sartre","isFavorite":false,"theme":"philosophy"},
     {"id":192,"text":"Qui ne tente rien n’a rien.","author":"Proverbe français","isFavorite":false,"theme":"motivation"},
     {"id":193,"text":"On ne naît pas femme : on le devient.","author":"Simone de Beauvoir","isFavorite":false,"theme":"literature"},
     {"id":194,"text":"La vie est un défi, relève-le !","author":"Mère Teresa","isFavorite":false,"theme":"motivation"},
     {"id":195,"text":"L’art est long, et le temps est court.","author":"Hippocrate","isFavorite":false,"theme":"art"},
     {"id":196,"text":"L’expérience est le nom que chacun donne à ses erreurs.","author":"Oscar Wilde","isFavorite":false,"theme":"wisdom"},
     {"id":197,"text":"La vie est un sommeil, l’amour en est le rêve, et vous aurez vécu si vous avez aimé.","author":"Alfred de Musset","isFavorite":false,"theme":"philosophy"},
     {"id":198,"text":"Tout est difficile avant d’être facile.","author":"Thomas Fuller","isFavorite":false,"theme":"motivation"},
     {"id":199,"text":"Ne remettez pas à demain ce que vous pouvez faire aujourd’hui.","author":"Benjamin Franklin","isFavorite":false,"theme":"motivation"},
     {"id":200,"text":"Les grandes choses ne sont jamais faites par une seule personne.","author":"Steve Jobs","isFavorite":false,"theme":"motivation"}
]
